drb_impl_zip/__init__.py
drb_impl_zip/_version.py
drb_impl_zip/cortex.yml
drb_impl_zip/execptions.py
drb_impl_zip/file_zip_node.py
drb_impl_zip/zip_node.py
drb_impl_zip-1.0.1.data/data/requirements.txt
drb_impl_zip-1.0.1.dist-info/METADATA
drb_impl_zip-1.0.1.dist-info/WHEEL
drb_impl_zip-1.0.1.dist-info/entry_points.txt
drb_impl_zip-1.0.1.dist-info/top_level.txt
drb_impl_zip-1.0.1.dist-info/RECORD
